MANIFEST.in
README.txt
setup.py
collective/__init__.py
collective.anonymousview.egg-info/PKG-INFO
collective.anonymousview.egg-info/SOURCES.txt
collective.anonymousview.egg-info/dependency_links.txt
collective.anonymousview.egg-info/entry_points.txt
collective.anonymousview.egg-info/namespace_packages.txt
collective.anonymousview.egg-info/not-zip-safe
collective.anonymousview.egg-info/requires.txt
collective.anonymousview.egg-info/top_level.txt
collective/anonymousview/__init__.py
collective/anonymousview/anonymousview.py
collective/anonymousview/configure.zcml
collective/anonymousview/interfaces.py
collective/anonymousview/Extensions/Install.py
collective/anonymousview/locales/collective.anonymousview.pot
collective/anonymousview/locales/rebuildPo.sh
collective/anonymousview/locales/it/LC_MESSAGES/collective.anonymousview.mo
collective/anonymousview/locales/it/LC_MESSAGES/collective.anonymousview.po
collective/anonymousview/profiles/default/actions.xml
collective/anonymousview/profiles/default/metadata.xml
collective/anonymousview/tests/__init__.py
collective/anonymousview/tests/anonymousview_integration.txt
collective/anonymousview/tests/base.py
collective/anonymousview/tests/test_anonymousview.py
docs/HISTORY.txt
docs/INSTALL.txt
docs/LICENSE.GPL
docs/LICENSE.txt