Metadata-Version: 1.0
Name: collective.anonymousview
Version: 1.1
Summary: Allow a loggedin user to view a page as an anonymous user
Home-page: http://svn.plone.org/svn/collective/collective.anonymousview
Author: Four Digits
Author-email: roel@fourdigits.nl
License: GPL
Platform: UNKNOWN
Classifier: Framework :: Plone
Classifier: Framework :: Plone :: 3.3
Classifier: Framework :: Plone :: 4.0
Classifier: Framework :: Plone :: 4.1
Classifier: Framework :: Plone :: 4.2
Classifier: Programming Language :: Python
Classifier: Topic :: Software Development :: Libraries :: Python Modules
